{
  "todos": [
    {
      "id": "1",
      "title": "TODO 1",
      "contents": "CONTENT1",
      "isDone": true
    },
    {
      "id": "2",
      "title": "TODO 2",
      "contents": "CONTENT2",
      "isDone": true
    },
    {
      "id": "8dc43b2e-4072-2637-7cb0-f9920b347870",
      "title": "신기하네요?",
      "contents": "",
      "isDone": true
    },
    {
      "id": "019b9fe3-217b-680b-86df-279e18811e4a",
      "title": "asdfasdfads",
      "contents": "",
      "isDone": false
    },
    {
      "id": "40123ede-4e2d-4c3a-17d1-4da90b643438",
      "title": "asdfasdfasdfasdf",
      "contents": "",
      "isDone": false
    },
    {
      "id": "9ed97672-8f6e-47c2-75dd-d32c58952544",
      "title": "asdfasdfasdf",
      "contents": "",
      "isDone": false
    }
  ]
}